funstrat/__init__.py
funstrat/main.py
funstrat/helpers/__init__.py
funstrat/helpers/array.py
funstrat/helpers/checks.py
funstrat/helpers/math.py
funstrat/helpers/pipeline/__init__.py
funstrat/helpers/pipeline/main.py
funstrat/helpers/pipeline/blocks/__init__.py
funstrat/helpers/pipeline/blocks/base.py
funstrat/helpers/pipeline/blocks/others.py
funstrat/helpers/pipeline/pipe/__init__.py
funstrat/helpers/pipeline/pipe/checks.py
funstrat/helpers/pipeline/pipe/network.py
funstrat/helpers/pipeline/pipe/pipe.py
funstrat/indicators/__init__.py
funstrat/indicators/atr.py
funstrat/indicators/fibb.py
funstrat/indicators/interface.py
funstrat/indicators/rsi.py
funstrat/indicators/tstate.py
funstrat-0.1.dist-info/METADATA
funstrat-0.1.dist-info/WHEEL
funstrat-0.1.dist-info/top_level.txt
funstrat-0.1.dist-info/RECORD
