Metadata-Version: 2.1
Name: funstrat
Version: 0.1
Summary: Preprocess the bars for the trading bot. 
Home-page: UNKNOWN
Author: Kevin Hill
Author-email: kevin@funguana.com
License: UNKNOWN
Platform: UNKNOWN
Classifier: Programming Language :: Python :: 3
Classifier: License :: OSI Approved :: MIT License
Classifier: Operating System :: OS Independent
Requires-Dist: crayons
Requires-Dist: spaceman
Requires-Dist: funhouse
Requires-Dist: TA-Lib
Requires-Dist: scikit-fuzzy
Requires-Dist: numpy
Requires-Dist: pandas
